fluyt_nightly-0.1.0.dev20200824181154.data/purelib/fluyt/__init__.py
fluyt_nightly-0.1.0.dev20200824181154.data/purelib/fluyt/core/__init__.py
fluyt_nightly-0.1.0.dev20200824181154.data/purelib/fluyt/core/python/__init__.py
fluyt_nightly-0.1.0.dev20200824181154.data/purelib/fluyt/core/python/api/__init__.py
fluyt_nightly-0.1.0.dev20200824181154.data/purelib/fluyt/core/python/api/ops.py
fluyt_nightly-0.1.0.dev20200824181154.data/purelib/fluyt/core/python/api/random.py
fluyt_nightly-0.1.0.dev20200824181154.data/purelib/fluyt/core/python/ops/__init__.py
fluyt_nightly-0.1.0.dev20200824181154.data/purelib/fluyt/core/python/ops/basic_ops.py
fluyt_nightly-0.1.0.dev20200824181154.data/purelib/fluyt/core/python/ops/core_ops.py
fluyt_nightly-0.1.0.dev20200824181154.data/purelib/fluyt/core/python/ops/random_ops.py
fluyt_nightly-0.1.0.dev20200824181154.dist-info/LICENSE
fluyt_nightly-0.1.0.dev20200824181154.dist-info/METADATA
fluyt_nightly-0.1.0.dev20200824181154.dist-info/WHEEL
fluyt_nightly-0.1.0.dev20200824181154.dist-info/top_level.txt
fluyt_nightly-0.1.0.dev20200824181154.dist-info/RECORD
