Metadata-Version: 2.1
Name: fluyt-nightly
Version: 0.1.0.dev20200824181154
Summary: UNKNOWN
Home-page: UNKNOWN
License: UNKNOWN
Platform: UNKNOWN
Requires-Python: >=3.6, <3.9
Requires-Dist: tensorflow
